{"version": "1", "message": "ERROR: Hidden Testcases server unreachable.", "problem_id": "ads1_m14_a2", "user_id": "lakshmipraneetha4", "score": {"sample": {"0": {"execution_time": 0.5523314476013184, "passed": true}, "1": {"execution_time": 0.40994930267333984, "passed": true}, "2": {"execution_time": 0.41140079498291016, "passed": true}, "3": {"execution_time": 0.3849153518676758, "passed": false}, "4": {"execution_time": 0.45786285400390625, "passed": false}, "5": {"execution_time": 0.42183399200439453, "passed": false}}}, "check_style_score": "0/1"}